__init__.py
lavanda.py
lavanda-0.0.2.dist-info/METADATA
lavanda-0.0.2.dist-info/WHEEL
lavanda-0.0.2.dist-info/top_level.txt
lavanda-0.0.2.dist-info/RECORD
